hstphot/__init__.py
hstphot/apphot.py
hstphot/background.py
hstphot/container.py
hstphot/cutout2d.py
hstphot/mag2flux.py
hstphot/objectmask.py
hstphot/phot2abmag.py
hstphot/photapcorr.py
hstphot/read_ds9region.py
hstphot/show_source.py
hstphot/show_sources.py
hstphot/show_sum1d.py
hstphot/to_fullframe.py
hstphot-1.3.0.dist-info/LICENSE
hstphot-1.3.0.dist-info/METADATA
hstphot-1.3.0.dist-info/WHEEL
hstphot-1.3.0.dist-info/top_level.txt
hstphot-1.3.0.dist-info/RECORD
